{
  "teeth": [
    {
      "id": 11,
      "name": "Incisivo Central Superior Derecho",
      "quadrant": "superior_derecho",
      "position": "central",
      "type": "incisor"
    },
    {
      "id": 12,
      "name": "Incisivo Lateral Superior Derecho",
      "quadrant": "superior_derecho",
      "position": "lateral",
      "type": "incisor"
    },
    {
      "id": 13,
      "name": "Canino Superior Derecho",
      "quadrant": "superior_derecho",
      "position": "canine",
      "type": "canine"
    },
    {
      "id": 14,
      "name": "Primer Premolar Superior Derecho",
      "quadrant": "superior_derecho",
      "position": "first_premolar",
      "type": "premolar"
    },
    {
      "id": 15,
      "name": "Segundo Premolar Superior Derecho",
      "quadrant": "superior_derecho",
      "position": "second_premolar",
      "type": "premolar"
    },
    {
      "id": 16,
      "name": "Primer Molar Superior Derecho",
      "quadrant": "superior_derecho",
      "position": "first_molar",
      "type": "molar"
    },
    {
      "id": 17,
      "name": "Segundo Molar Superior Derecho",
      "quadrant": "superior_derecho",
      "position": "second_molar",
      "type": "molar"
    },
    {
      "id": 18,
      "name": "Tercer Molar Superior Derecho (Cordal)",
      "quadrant": "superior_derecho",
      "position": "third_molar",
      "type": "molar"
    },
    {
      "id": 21,
      "name": "Incisivo Central Superior Izquierdo",
      "quadrant": "superior_izquierdo",
      "position": "central",
      "type": "incisor"
    },
    {
      "id": 22,
      "name": "Incisivo Lateral Superior Izquierdo",
      "quadrant": "superior_izquierdo",
      "position": "lateral",
      "type": "incisor"
    },
    {
      "id": 23,
      "name": "Canino Superior Izquierdo",
      "quadrant": "superior_izquierdo",
      "position": "canine",
      "type": "canine"
    },
    {
      "id": 24,
      "name": "Primer Premolar Superior Izquierdo",
      "quadrant": "superior_izquierdo",
      "position": "first_premolar",
      "type": "premolar"
    },
    {
      "id": 25,
      "name": "Segundo Premolar Superior Izquierdo",
      "quadrant": "superior_izquierdo",
      "position": "second_premolar",
      "type": "premolar"
    },
    {
      "id": 26,
      "name": "Primer Molar Superior Izquierdo",
      "quadrant": "superior_izquierdo",
      "position": "first_molar",
      "type": "molar"
    },
    {
      "id": 27,
      "name": "Segundo Molar Superior Izquierdo",
      "quadrant": "superior_izquierdo",
      "position": "second_molar",
      "type": "molar"
    },
    {
      "id": 28,
      "name": "Tercer Molar Superior Izquierdo (Cordal)",
      "quadrant": "superior_izquierdo",
      "position": "third_molar",
      "type": "molar"
    },
    {
      "id": 31,
      "name": "Incisivo Central Inferior Izquierdo",
      "quadrant": "inferior_izquierdo",
      "position": "central",
      "type": "incisor"
    },
    {
      "id": 32,
      "name": "Incisivo Lateral Inferior Izquierdo",
      "quadrant": "inferior_izquierdo",
      "position": "lateral",
      "type": "incisor"
    },
    {
      "id": 33,
      "name": "Canino Inferior Izquierdo",
      "quadrant": "inferior_izquierdo",
      "position": "canine",
      "type": "canine"
    },
    {
      "id": 34,
      "name": "Primer Premolar Inferior Izquierdo",
      "quadrant": "inferior_izquierdo",
      "position": "first_premolar",
      "type": "premolar"
    },
    {
      "id": 35,
      "name": "Segundo Premolar Inferior Izquierdo",
      "quadrant": "inferior_izquierdo",
      "position": "second_premolar",
      "type": "premolar"
    },
    {
      "id": 36,
      "name": "Primer Molar Inferior Izquierdo",
      "quadrant": "inferior_izquierdo",
      "position": "first_molar",
      "type": "molar"
    },
    {
      "id": 37,
      "name": "Segundo Molar Inferior Izquierdo",
      "quadrant": "inferior_izquierdo",
      "position": "second_molar",
      "type": "molar"
    },
    {
      "id": 38,
      "name": "Tercer Molar Inferior Izquierdo (Cordal)",
      "quadrant": "inferior_izquierdo",
      "position": "third_molar",
      "type": "molar"
    },
    {
      "id": 41,
      "name": "Incisivo Central Inferior Derecho",
      "quadrant": "inferior_derecho",
      "position": "central",
      "type": "incisor"
    },
    {
      "id": 42,
      "name": "Incisivo Lateral Inferior Derecho",
      "quadrant": "inferior_derecho",
      "position": "lateral",
      "type": "incisor"
    },
    {
      "id": 43,
      "name": "Canino Inferior Derecho",
      "quadrant": "inferior_derecho",
      "position": "canine",
      "type": "canine"
    },
    {
      "id": 44,
      "name": "Primer Premolar Inferior Derecho",
      "quadrant": "inferior_derecho",
      "position": "first_premolar",
      "type": "premolar"
    },
    {
      "id": 45,
      "name": "Segundo Premolar Inferior Derecho",
      "quadrant": "inferior_derecho",
      "position": "second_premolar",
      "type": "premolar"
    },
    {
      "id": 46,
      "name": "Primer Molar Inferior Derecho",
      "quadrant": "inferior_derecho",
      "position": "first_molar",
      "type": "molar"
    },
    {
      "id": 47,
      "name": "Segundo Molar Inferior Derecho",
      "quadrant": "inferior_derecho",
      "position": "second_molar",
      "type": "molar"
    },
    {
      "id": 48,
      "name": "Tercer Molar Inferior Derecho (Cordal)",
      "quadrant": "inferior_derecho",
      "position": "third_molar",
      "type": "molar"
    }
  ]
}